custom_math_operations/__init__.py
custom_math_operations/operations.py
math_operations/__init__.py
math_operations/operations.py
custom_math_operations_gangulis-0.0.2.dist-info/LICENSE.txt
custom_math_operations_gangulis-0.0.2.dist-info/METADATA
custom_math_operations_gangulis-0.0.2.dist-info/WHEEL
custom_math_operations_gangulis-0.0.2.dist-info/top_level.txt
custom_math_operations_gangulis-0.0.2.dist-info/RECORD
